[
  {
    "direction": "Flat", 
    "noise": 1, 
    "sysTime": "2016-03-27T06:39:23.307-0700", 
    "xDrip_calculated_value": 98, 
    "xDrip_raw": 109, 
    "dateString": "2016-03-27T06:39:23.307-0700", 
    "sgv": 98, 
    "date": 1459085963307, 
    "xDrip_filtered": 109, 
    "xDrip_age_adjusted_raw_value": 109, 
    "unfiltered": 109000, 
    "rssi": 100, 
    "device": "xDrip-DexcomShare", 
    "filtered": 109000, 
    "xDrip_calculated_current_slope": -1.001669449081803e-05, 
    "_id": "56f7e2ac65110bbfc192913c", 
    "type": "sgv"
  }, 
  {
    "direction": "Flat", 
    "noise": 1, 
    "sysTime": "2016-03-27T06:34:23.807-0700", 
    "xDrip_calculated_value": 101, 
    "xDrip_raw": 111, 
    "dateString": "2016-03-27T06:34:23.807-0700", 
    "sgv": 101, 
    "date": 1459085663807, 
    "xDrip_filtered": 108, 
    "xDrip_age_adjusted_raw_value": 111, 
    "unfiltered": 111000, 
    "rssi": 100, 
    "device": "xDrip-DexcomShare", 
    "filtered": 108000, 
    "xDrip_calculated_current_slope": 6.653337813247461e-06, 
    "_id": "56f7e1a365110bbfc192913b", 
    "type": "sgv"
  }, 
  {
    "direction": "Flat", 
    "noise": 1, 
    "sysTime": "2016-03-27T06:29:23.206-0700", 
    "xDrip_calculated_value": 99, 
    "xDrip_raw": 109, 
    "dateString": "2016-03-27T06:29:23.206-0700", 
    "sgv": 99, 
    "date": 1459085363206, 
    "xDrip_filtered": 107, 
    "xDrip_age_adjusted_raw_value": 109, 
    "unfiltered": 109000, 
    "rssi": 100, 
    "device": "xDrip-DexcomShare", 
    "filtered": 107000, 
    "xDrip_calculated_current_slope": 3.3359910061682475e-06, 
    "_id": "56f7e05465110bbfc1929137", 
    "type": "sgv"
  }, 
  {
    "direction": "Flat", 
    "noise": 1, 
    "sysTime": "2016-03-27T06:24:23.445-0700", 
    "xDrip_calculated_value": 98, 
    "xDrip_raw": 108, 
    "dateString": "2016-03-27T06:24:23.445-0700", 
    "sgv": 98, 
    "date": 1459085063445, 
    "xDrip_filtered": 109, 
    "xDrip_age_adjusted_raw_value": 108, 
    "unfiltered": 108000, 
    "rssi": 100, 
    "device": "xDrip-DexcomShare", 
    "filtered": 109000, 
    "xDrip_calculated_current_slope": 3.3357573169836747e-06, 
    "_id": "56f7df2765110bbfc1929136", 
    "type": "sgv"
  }, 
  {
    "direction": "Flat", 
    "noise": 1, 
    "sysTime": "2016-03-27T06:19:23.663-0700", 
    "xDrip_calculated_value": 97, 
    "xDrip_raw": 107, 
    "dateString": "2016-03-27T06:19:23.663-0700", 
    "sgv": 97, 
    "date": 1459084763663, 
    "xDrip_filtered": 113, 
    "xDrip_age_adjusted_raw_value": 107, 
    "unfiltered": 107000, 
    "rssi": 100, 
    "device": "xDrip-DexcomShare", 
    "filtered": 113000, 
    "xDrip_calculated_current_slope": -6.677907811482663e-06, 
    "_id": "56f7de1d65110bbfc1929134", 
    "type": "sgv"
  }, 
  {
    "direction": "Flat", 
    "noise": 1, 
    "sysTime": "2016-03-27T06:14:24.168-0700", 
    "xDrip_calculated_value": 99, 
    "xDrip_raw": 110, 
    "dateString": "2016-03-27T06:14:24.168-0700", 
    "sgv": 99, 
    "date": 1459084464168, 
    "xDrip_filtered": 117, 
    "xDrip_age_adjusted_raw_value": 110, 
    "unfiltered": 110000, 
    "rssi": 100, 
    "device": "xDrip-DexcomShare", 
    "filtered": 117000, 
    "xDrip_calculated_current_slope": -1.995271207238844e-05, 
    "_id": "56f7dcce65110bbfc1929133", 
    "type": "sgv"
  }, 
  {
    "direction": "Flat", 
    "noise": 1, 
    "sysTime": "2016-03-27T06:09:23.457-0700", 
    "xDrip_calculated_value": 105, 
    "xDrip_raw": 115, 
    "dateString": "2016-03-27T06:09:23.457-0700", 
    "sgv": 105, 
    "date": 1459084163457, 
    "xDrip_filtered": 120, 
    "xDrip_age_adjusted_raw_value": 115, 
    "unfiltered": 115000, 
    "rssi": 100, 
    "device": "xDrip-DexcomShare", 
    "filtered": 120000, 
    "xDrip_calculated_current_slope": -1.0024225210926406e-05, 
    "_id": "56f7dba265110bbfc192912f", 
    "type": "sgv"
  }, 
  {
    "direction": "Flat", 
    "noise": 1, 
    "sysTime": "2016-03-27T06:04:24.182-0700", 
    "xDrip_calculated_value": 108, 
    "xDrip_raw": 118, 
    "dateString": "2016-03-27T06:04:24.182-0700", 
    "sgv": 108, 
    "date": 1459083864182, 
    "xDrip_filtered": 120, 
    "xDrip_age_adjusted_raw_value": 118, 
    "unfiltered": 118000, 
    "rssi": 100, 
    "device": "xDrip-DexcomShare", 
    "filtered": 120000, 
    "xDrip_calculated_current_slope": -1.3296236832570461e-05, 
    "_id": "56f7da9665110bbfc192912e", 
    "type": "sgv"
  }, 
  {
    "direction": "Flat", 
    "noise": 1, 
    "sysTime": "2016-03-27T05:59:23.345-0700", 
    "xDrip_calculated_value": 112, 
    "xDrip_raw": 121, 
    "dateString": "2016-03-27T05:59:23.345-0700", 
    "sgv": 112, 
    "date": 1459083563345, 
    "xDrip_filtered": 120, 
    "xDrip_age_adjusted_raw_value": 121, 
    "unfiltered": 121000, 
    "rssi": 100, 
    "device": "xDrip-DexcomShare", 
    "filtered": 120000, 
    "xDrip_calculated_current_slope": 0, 
    "_id": "56f7d94965110bbfc192912d", 
    "type": "sgv"
  }, 
  {
    "direction": "Flat", 
    "noise": 1, 
    "sysTime": "2016-03-27T05:54:23.627-0700", 
    "xDrip_calculated_value": 112, 
    "xDrip_raw": 121, 
    "dateString": "2016-03-27T05:54:23.627-0700", 
    "sgv": 112, 
    "date": 1459083263627, 
    "xDrip_filtered": 119, 
    "xDrip_age_adjusted_raw_value": 121, 
    "unfiltered": 121000, 
    "rssi": 100, 
    "device": "xDrip-DexcomShare", 
    "filtered": 119000, 
    "xDrip_calculated_current_slope": 3.3265693090715544e-06, 
    "_id": "56f7d88765110bbfc192912c", 
    "type": "sgv"
  }
]